minecraft_backup/__init__.py
minecraft_backup/__main__.py
minecraft_backup/main.py
minecraft_backup/commands/__init__.py
minecraft_backup/commands/log_clear.py
minecraft_backup/commands/server_backup.py
minecraft_backup/commands/user_config.py
minecraft_backup/config/__init__.py
minecraft_backup/config/log_config.py
minecraft_backup/config/user_config.py
minecraft_backup/convenience/__init__.py
minecraft_backup/convenience/files.py
minecraft_backup/convenience/logs.py
minecraft_backup/convenience/user_config.py
minecraft_backup/data/log_config.json
minecraft_backup/data/user_config.json
minecraft_backup/data/logs/logfile.log
minecraft_backup-1.0.1.dist-info/LICENSE
minecraft_backup-1.0.1.dist-info/METADATA
minecraft_backup-1.0.1.dist-info/WHEEL
minecraft_backup-1.0.1.dist-info/entry_points.txt
minecraft_backup-1.0.1.dist-info/top_level.txt
minecraft_backup-1.0.1.dist-info/RECORD
