Metadata-Version: 2.1
Name: minecraft-backup
Version: 1.0.1
Summary: This is a backup management library for Minecraft servers. It should be run and used on a regular basis using cron or similar. 
Home-page: https://github.com/HEKUCHAN/minecraft_server_backup_python
Author: Heitor Hirose
Author-email: Heitorhirose@gmail.com
License: MIT License
Keywords: Image Registration
Platform: UNKNOWN
Classifier: Development Status :: 1 - Planning
Classifier: Environment :: Console
Classifier: License :: OSI Approved :: MIT License
Classifier: Natural Language :: English
Classifier: Operating System :: Microsoft :: Windows :: Windows 10
Classifier: Programming Language :: Python :: 3.6
Requires-Python: >=3.6.8
Requires-Dist: pathlib
Requires-Dist: argparse
Requires-Dist: fabric3
